igg_games_tools/__init__.py
igg_games_tools/__main__.py
igg_games_tools/bing_steamdb.py
igg_games_tools/google_igg_games_search.py
igg_games_tools/igg_games.py
igg_games_tools/megaup.py
igg_games_tools-0.2.0.dist-info/entry_points.txt
igg_games_tools-0.2.0.dist-info/METADATA
igg_games_tools-0.2.0.dist-info/WHEEL
igg_games_tools-0.2.0.dist-info/RECORD
