Metadata-Version: 2.1
Name: igg-games-tools
Version: 0.2.0
Summary: 
Author: jawide
Author-email: jawide@qq.com
Requires-Python: >=3.8,<4.0
Classifier: Programming Language :: Python :: 3
Classifier: Programming Language :: Python :: 3.8
Classifier: Programming Language :: Python :: 3.9
Classifier: Programming Language :: Python :: 3.10
Classifier: Programming Language :: Python :: 3.11
Requires-Dist: bs4
Requires-Dist: fake_useragent
Requires-Dist: requests
